{
  "type": "object",
  "properties": {
    "lastname": {
      "type": "string",
      "maxLength": 20
    },
    "firstname": {
      "type": "string",
      "maxLength": 10
    },
    "workphone": {
      "type": "string"
    },
    "mobilephone": {
      "type": "string"
    },
    "mail": {
      "type": "string",
      "pattern": "^(?=.{1,41}$)(\\S){1,30}@(\\S){1,10}$"
    },
    "birthdate": {
      "type": "string",
      "format": "date"
    }
  },
  "required": [
    "lastname",
    "firstname",
    "workphone",
    "mobilephone",
    "mail",
    "birthdate"
  ]
}